aws_myfa/__init__.py
aws_myfa/__main__.py
victorykit_aws_myfa-1.0.0.dist-info/LICENSE
victorykit_aws_myfa-1.0.0.dist-info/METADATA
victorykit_aws_myfa-1.0.0.dist-info/NOTICE.md
victorykit_aws_myfa-1.0.0.dist-info/WHEEL
victorykit_aws_myfa-1.0.0.dist-info/entry_points.txt
victorykit_aws_myfa-1.0.0.dist-info/top_level.txt
victorykit_aws_myfa-1.0.0.dist-info/zip-safe
victorykit_aws_myfa-1.0.0.dist-info/RECORD
