Metadata-Version: 2.1
Name: victorykit-aws-myfa
Version: 1.0.0
Summary: Convenience wrapper for MFA-authenticated AWS STS sessions
Home-page: https://victorykit.bitbucket.io/py-aws-myfa
Author: Tiara Rodney (victory-k.it)
Author-email: py-aws-mfa@victoryk.it
Project-URL: Bug Tracker, https://bitbucket.org/victorykit/py-aws-myfa/jira
Classifier: Development Status :: 4 - Beta
Classifier: Environment :: Other Environment
Classifier: Intended Audience :: Developers
Classifier: Topic :: Utilities
Classifier: Topic :: Security
Classifier: Programming Language :: Python :: 3.7
Classifier: Programming Language :: Python :: 3.8
Classifier: Programming Language :: Python :: 3.9
Classifier: Operating System :: OS Independent
Classifier: License :: Other/Proprietary License
Requires-Python: >=3.7
License-File: LICENSE
License-File: NOTICE.md
